pythonGraphicalManipulator/__init__.py
pythonGraphicalManipulator-0.1.0.dist-info/LICENSE
pythonGraphicalManipulator-0.1.0.dist-info/METADATA
pythonGraphicalManipulator-0.1.0.dist-info/WHEEL
pythonGraphicalManipulator-0.1.0.dist-info/top_level.txt
pythonGraphicalManipulator-0.1.0.dist-info/RECORD
