Metadata-Version: 2.2
Name: pythonGraphicalManipulator
Version: 0.1.0
Summary: A python library for graphical image manipulation
Home-page: https://github.com/salchaD-27/pythonGraphicalManipulator.git
Author: Dharyansh Achlas
Classifier: Programming Language :: Python :: 3
Classifier: License :: OSI Approved :: MIT License
Classifier: Operating System :: OS Independent
Requires-Python: >=3.6
License-File: LICENSE
Requires-Dist: Pillow>=9.0.0
Dynamic: author
Dynamic: classifier
Dynamic: description
Dynamic: description-content-type
Dynamic: home-page
Dynamic: requires-dist
Dynamic: requires-python
Dynamic: summary
